Metadata-Version: 2.1
Name: vtt_to_srt3
Version: 0.2.0.4
Summary: vtt to srt subtitles converter package
Home-page: https://github.com/jsonzilla/vtt_to_srt3
Author: Jeison Cardoso
Author-email: j@jsonzilla.com
Maintainer: Jeison Cardoso
Classifier: Programming Language :: Python :: 3.7
Classifier: Programming Language :: Python :: 3.8
Classifier: Programming Language :: Python :: 3.9
Classifier: Programming Language :: Python :: 3.10
Classifier: Programming Language :: Python :: 3.11
Classifier: Operating System :: OS Independent
License-File: LICENSE
